tahoestaticfs
