Metadata-Version: 2.1
Name: tahoestaticfs
Version: 0.1.1
Summary: Fuse filesystem on Tahoe-LAFS
License: AGPLv3+
Project-URL: Source, https://github.com/pv/tahoestaticfs
Classifier: Programming Language :: Python :: 3
Classifier: License :: OSI Approved :: GNU Affero General Public License v3 or later (AGPLv3+)
Requires-Python: >=3.7
Provides-Extra: test
License-File: LICENSE.txt
